custom_logger/__init__.py
custom_logger/context_threading.py
custom_logger/custom_logger.py
custom_logger/decorators.py
python_context_logger-1.0.2.dist-info/METADATA
python_context_logger-1.0.2.dist-info/WHEEL
python_context_logger-1.0.2.dist-info/top_level.txt
python_context_logger-1.0.2.dist-info/RECORD
