Metadata-Version: 2.1
Name: python_context_logger
Version: 1.0.2
Summary: A context custom logger with thread-local storage and context propagation for Python applications.
Home-page: 
Author: Rajesh Ganjikunta
Author-email: rajeshkumarganjikunta90@gmail.com
License: MIT
Classifier: Development Status :: 3 - Alpha
Classifier: Intended Audience :: Developers
Classifier: License :: OSI Approved :: MIT License
Classifier: Programming Language :: Python :: 3
Classifier: Programming Language :: Python :: 3.7
Classifier: Programming Language :: Python :: 3.8
Classifier: Programming Language :: Python :: 3.9
Classifier: Programming Language :: Python :: 3.10
Classifier: Programming Language :: Python :: 3.11
